<?xml version="1.0" encoding="UTF-8"?>
<objects serializationModel="Studio.02.03.00">
	<object class="AudioFile" id="{eb54127c-d2f6-4c4a-9b2d-8b0b87b2b291}">
		<property name="assetPath">
			<value>SFX/Player/Attack/Staff/Swing/Weapons, Sword, Sword, Whoosh, Pitched Down 05 SND69305 1.wav</value>
		</property>
		<property name="frequencyInKHz">
			<value>96</value>
		</property>
		<property name="channelCount">
			<value>2</value>
		</property>
		<property name="length">
			<value>0.72888541666666662</value>
		</property>
		<relationship name="masterAssetFolder">
			<destination>{b16508f5-40a4-4ecc-9a7d-843f135e876d}</destination>
		</relationship>
	</object>
</objects>
